ivt.py
pyrego600/__init__.py
pyrego600/checksum.py
pyrego600/connection.py
pyrego600/group.py
pyrego600/heatpump.py
pyrego600/identifier.py
pyrego600/identifiers.py
pyrego600/last_error.py
pyrego600/register.py
pyrego600/register_factory.py
pyrego600/register_repository.py
pyrego600/regoerror.py
pyrego600/serial_connection.py
pyrego600/source.py
pyrego600/sources.py
pyrego600/type.py
pyrego600/value_converter.py
pyrego600/decoders/__init__.py
pyrego600/decoders/abstract_decoder.py
pyrego600/decoders/decoder.py
pyrego600/decoders/decoders.py
pyrego600/decoders/empty_decoder.py
pyrego600/decoders/error_decoder.py
pyrego600/decoders/int16_decoder.py
pyrego600/transformations/__init__.py
pyrego600/transformations/identity_transformation.py
pyrego600/transformations/numeric_transformation.py
pyrego600/transformations/transformation.py
pyrego600/transformations/transformations.py
pyrego600-0.0.6.dist-info/LICENCE
pyrego600-0.0.6.dist-info/METADATA
pyrego600-0.0.6.dist-info/WHEEL
pyrego600-0.0.6.dist-info/top_level.txt
pyrego600-0.0.6.dist-info/RECORD
