Metadata-Version: 2.2
Name: pyrego600
Version: 0.0.6
Summary: A small example package
Author-email: Boris Krivonog <boris.krivonog@inova.si>
Project-URL: Homepage, https://github.com/crnjan/pyrego600
Project-URL: Issues, https://github.com/crnjan/pyrego600/issues
Classifier: Programming Language :: Python :: 3
Classifier: Operating System :: OS Independent
Requires-Python: >=3.11
License-File: LICENCE
Requires-Dist: pyserial-asyncio-fast==0.14
Provides-Extra: dev
Requires-Dist: pytest; extra == "dev"
Requires-Dist: pytest-asyncio; extra == "dev"
Requires-Dist: ruff; extra == "dev"
